seatools/ioc/starters/gunicorn/__init__.py
seatools/ioc/starters/gunicorn/wsgiapp.py
seatools_starter_server_gunicorn-1.0.0.dist-info/METADATA
seatools_starter_server_gunicorn-1.0.0.dist-info/WHEEL
seatools_starter_server_gunicorn-1.0.0.dist-info/entry_points.txt
seatools_starter_server_gunicorn-1.0.0.dist-info/licenses/LICENSE
seatools_starter_server_gunicorn-1.0.0.dist-info/RECORD
