Metadata-Version: 2.4
Name: seatools-starter-server-gunicorn
Version: 1.0.0
Summary: Seatools gunicorn server starter.
Project-URL: Homepage, https://github.com/seatools-py/seatools-starter-server-gunicorn
Project-URL: Issues, https://github.com/seatools-py/seatools-starter-server-gunicorn/issues
Author-email: seatools-py <521274311@qq.com>
License-Expression: MIT
License-File: LICENSE
Keywords: seatools,starter
Classifier: License :: OSI Approved :: MIT License
Classifier: Operating System :: OS Independent
Classifier: Programming Language :: Python :: 3
Requires-Python: >=3.9
Requires-Dist: gunicorn
Requires-Dist: seatools
